Metadata-Version: 2.1
Name: Flask-Web-Log
Version: 0.1
Summary: Enables web traffic and request logs for your Flask app.
Home-page: https://github.com/nethunterslabs/flask-web-log
Author: Nethunters Dev
Author-email: dev@nethunters.co.uk
License: Apache 2.0
Download-URL: https://github.com/nethunterslabs/flask-web-log/archive/0.1.tar.gz
Platform: any
Classifier: Environment :: Web Environment
Classifier: Intended Audience :: Developers
Classifier: Framework :: Flask
Classifier: License :: OSI Approved :: Apache Software License
Classifier: Operating System :: OS Independent
Classifier: Programming Language :: Python
Classifier: Topic :: Internet :: WWW/HTTP :: Dynamic Content
Classifier: Topic :: Software Development :: Libraries :: Python Modules
